bolthole/__init__.py
bolthole/cli.py
bolthole/debounce.py
bolthole/git.py
bolthole/watcher.py
bolthole-1.0.2.dist-info/METADATA
bolthole-1.0.2.dist-info/WHEEL
bolthole-1.0.2.dist-info/entry_points.txt
bolthole-1.0.2.dist-info/RECORD
