Metadata-Version: 2.4
Name: bolthole
Version: 1.0.2
Summary: bolthole
Author-email: Mark Norman Francis <norm@201created.com>
License-Expression: MIT
Requires-Python: >=3.10
Requires-Dist: watchdog
Provides-Extra: dev
Requires-Dist: flake8; extra == 'dev'
Requires-Dist: pytest; extra == 'dev'
